Chaeslib.py
Chaeslib-1.0.1.dist-info/LICENSE
Chaeslib-1.0.1.dist-info/METADATA
Chaeslib-1.0.1.dist-info/WHEEL
Chaeslib-1.0.1.dist-info/top_level.txt
Chaeslib-1.0.1.dist-info/RECORD
