Metadata-Version: 2.1
Name: Chaeslib
Version: 1.0.1
Summary: A minimalistic and simple AES256-GCM+ChaCha20_Poly1305 library. For encrypting data using both 'AES256-GCM' & 'ChaCha20_Poly1305'.
Home-page: https://github.com/therealOri/Chaeslib
Author: therealOri
Author-email: therealOri@duck.com
License: GPL-3.0
License-File: LICENSE
Requires-Dist: alive-progress
Requires-Dist: pycryptodome
Requires-Dist: argon2-cffi
